llmstudio_tracker/__init__.py
llmstudio_tracker/cli.py
llmstudio_tracker/config.py
llmstudio_tracker/database.py
llmstudio_tracker/db_utils.py
llmstudio_tracker/logs/__init__.py
llmstudio_tracker/logs/crud.py
llmstudio_tracker/logs/endpoints.py
llmstudio_tracker/logs/models.py
llmstudio_tracker/logs/schemas.py
llmstudio_tracker/prompt_manager/__init__.py
llmstudio_tracker/prompt_manager/crud.py
llmstudio_tracker/prompt_manager/endpoints.py
llmstudio_tracker/prompt_manager/manager.py
llmstudio_tracker/prompt_manager/models.py
llmstudio_tracker/prompt_manager/schemas.py
llmstudio_tracker/server.py
llmstudio_tracker/session/__init__.py
llmstudio_tracker/session/crud.py
llmstudio_tracker/session/endpoints.py
llmstudio_tracker/session/models.py
llmstudio_tracker/session/schemas.py
llmstudio_tracker/tracker.py
llmstudio_tracker/utils.py
llmstudio_tracker-1.1.1.dist-info/METADATA
llmstudio_tracker-1.1.1.dist-info/WHEEL
llmstudio_tracker-1.1.1.dist-info/entry_points.txt
llmstudio_tracker-1.1.1.dist-info/RECORD
