Metadata-Version: 2.1
Name: llmstudio-tracker
Version: 1.1.1
Summary: LLMstudio Tracker is the module of LLMstudio that allows monitoring and logging your LLM calls. By leveraging LLMstudio Tracker, users can gain insights on model performance and streamline development workflows with actionable analytics.
Author: Claudio Lemos
Author-email: claudio.lemos@tensorops.ai
Requires-Python: >=3.9,<3.13
Classifier: Programming Language :: Python :: 3
Classifier: Programming Language :: Python :: 3.9
Classifier: Programming Language :: Python :: 3.10
Classifier: Programming Language :: Python :: 3.11
Classifier: Programming Language :: Python :: 3.12
Requires-Dist: fastapi (>=0.115.5,<0.116.0)
Requires-Dist: google-cloud-bigquery-storage (>=2.27.0,<3.0.0)
Requires-Dist: pydantic (>=2.5,<3.0)
Requires-Dist: requests (>=2.31,<3.0)
Requires-Dist: sqlalchemy (>=2,<3)
Requires-Dist: sqlalchemy-bigquery (>=1.12.0,<2.0.0)
Requires-Dist: toml (>=0.10,<0.11)
Requires-Dist: uvicorn (>=0.27,<0.28)
